designate_tempest_plugin/__init__.py
designate_tempest_plugin/clients.py
designate_tempest_plugin/config.py
designate_tempest_plugin/data_utils.py
designate_tempest_plugin/plugin.py
designate_tempest_plugin/common/__init__.py
designate_tempest_plugin/common/constants.py
designate_tempest_plugin/common/exceptions.py
designate_tempest_plugin/common/models.py
designate_tempest_plugin/common/waiters.py
designate_tempest_plugin/hacking/__init__.py
designate_tempest_plugin/hacking/checks.py
designate_tempest_plugin/schemas/__init__.py
designate_tempest_plugin/schemas/v1/__init__.py
designate_tempest_plugin/schemas/v1/domains_schema.py
designate_tempest_plugin/schemas/v1/records_schema.py
designate_tempest_plugin/schemas/v1/servers_schema.py
designate_tempest_plugin/services/__init__.py
designate_tempest_plugin/services/dns/__init__.py
designate_tempest_plugin/services/dns/admin/__init__.py
designate_tempest_plugin/services/dns/admin/json/__init__.py
designate_tempest_plugin/services/dns/admin/json/base.py
designate_tempest_plugin/services/dns/admin/json/quotas_client.py
designate_tempest_plugin/services/dns/json/__init__.py
designate_tempest_plugin/services/dns/json/base.py
designate_tempest_plugin/services/dns/query/__init__.py
designate_tempest_plugin/services/dns/query/query_client.py
designate_tempest_plugin/services/dns/v2/__init__.py
designate_tempest_plugin/services/dns/v2/json/__init__.py
designate_tempest_plugin/services/dns/v2/json/api_version_client.py
designate_tempest_plugin/services/dns/v2/json/base.py
designate_tempest_plugin/services/dns/v2/json/blacklists_client.py
designate_tempest_plugin/services/dns/v2/json/designate_limit_client.py
designate_tempest_plugin/services/dns/v2/json/pool_client.py
designate_tempest_plugin/services/dns/v2/json/ptr_client.py
designate_tempest_plugin/services/dns/v2/json/quotas_client.py
designate_tempest_plugin/services/dns/v2/json/recordset_client.py
designate_tempest_plugin/services/dns/v2/json/service_client.py
designate_tempest_plugin-0.27.0.dist-info/AUTHORS
designate_tempest_plugin-0.27.0.dist-info/LICENSE
designate_tempest_plugin-0.27.0.dist-info/METADATA
designate_tempest_plugin-0.27.0.dist-info/WHEEL
designate_tempest_plugin-0.27.0.dist-info/entry_points.txt
designate_tempest_plugin-0.27.0.dist-info/pbr.json
designate_tempest_plugin-0.27.0.dist-info/top_level.txt
designate_tempest_plugin-0.27.0.dist-info/RECORD
