Metadata-Version: 2.1
Name: designate-tempest-plugin
Version: 0.27.0
Summary: OpenStack DNS As A Service (Designate) Functional Tests
Home-page: https://docs.openstack.org/designate-tempest-plugin/latest/
Author: OpenStack
Author-email: openstack-discuss@lists.openstack.org
Classifier: Environment :: OpenStack
Classifier: Environment :: No Input/Output (Daemon)
Classifier: Intended Audience :: Information Technology
Classifier: Intended Audience :: System Administrators
Classifier: License :: OSI Approved :: Apache Software License
Classifier: Operating System :: POSIX :: Linux
Classifier: Programming Language :: Python
Classifier: Programming Language :: Python :: Implementation :: CPython
Classifier: Programming Language :: Python :: 3 :: Only
Classifier: Programming Language :: Python :: 3
Classifier: Programming Language :: Python :: 3.10
Classifier: Programming Language :: Python :: 3.11
Classifier: Programming Language :: Python :: 3.12
Classifier: Topic :: Internet :: Name Service (DNS)
Requires-Python: >=3.10
License-File: LICENSE
License-File: AUTHORS
Requires-Dist: dnspython >=1.16.0
Requires-Dist: oslo.serialization >=2.25.0
Requires-Dist: oslo.utils >=3.33.0
Requires-Dist: testtools >=2.2.0
Requires-Dist: tempest >=17.1.0
